<annotation>
	<folder>images</folder>
	<filename>18_16_17_19_22_24_L_H_L_H_L_L_0560_0_6626.png</filename>
	<path>/Users/jesperchristensen/Dropbox/MSc/semester_3/02456_DeepLearning/Project/Tensorflow_object_detection/images/18_16_17_19_22_24_L_H_L_H_L_L_0560_0_6626.png</path>
	<source>
		<database>Unknown</database>
	</source>
	<size>
		<width>512</width>
		<height>512</height>
		<depth>3</depth>
	</size>
	<segmented>0</segmented>
	<object>
		<name>top</name>
		<pose>Unspecified</pose>
		<truncated>0</truncated>
		<difficult>0</difficult>
		<bndbox>
			<xmin>131</xmin>
			<ymin>135</ymin>
			<xmax>160</xmax>
			<ymax>168</ymax>
		</bndbox>
	</object>
	<object>
		<name>top</name>
		<pose>Unspecified</pose>
		<truncated>0</truncated>
		<difficult>0</difficult>
		<bndbox>
			<xmin>171</xmin>
			<ymin>130</ymin>
			<xmax>200</xmax>
			<ymax>162</ymax>
		</bndbox>
	</object>
	<object>
		<name>top</name>
		<pose>Unspecified</pose>
		<truncated>0</truncated>
		<difficult>0</difficult>
		<bndbox>
			<xmin>212</xmin>
			<ymin>125</ymin>
			<xmax>241</xmax>
			<ymax>155</ymax>
		</bndbox>
	</object>
	<object>
		<name>top</name>
		<pose>Unspecified</pose>
		<truncated>0</truncated>
		<difficult>0</difficult>
		<bndbox>
			<xmin>254</xmin>
			<ymin>118</ymin>
			<xmax>282</xmax>
			<ymax>156</ymax>
		</bndbox>
	</object>
	<object>
		<name>top</name>
		<pose>Unspecified</pose>
		<truncated>0</truncated>
		<difficult>0</difficult>
		<bndbox>
			<xmin>293</xmin>
			<ymin>107</ymin>
			<xmax>324</xmax>
			<ymax>148</ymax>
		</bndbox>
	</object>
	<object>
		<name>top</name>
		<pose>Unspecified</pose>
		<truncated>0</truncated>
		<difficult>0</difficult>
		<bndbox>
			<xmin>335</xmin>
			<ymin>102</ymin>
			<xmax>369</xmax>
			<ymax>144</ymax>
		</bndbox>
	</object>
	<object>
		<name>bottom</name>
		<pose>Unspecified</pose>
		<truncated>0</truncated>
		<difficult>0</difficult>
		<bndbox>
			<xmin>152</xmin>
			<ymin>329</ymin>
			<xmax>185</xmax>
			<ymax>371</ymax>
		</bndbox>
	</object>
	<object>
		<name>bottom</name>
		<pose>Unspecified</pose>
		<truncated>0</truncated>
		<difficult>0</difficult>
		<bndbox>
			<xmin>190</xmin>
			<ymin>313</ymin>
			<xmax>221</xmax>
			<ymax>353</ymax>
		</bndbox>
	</object>
	<object>
		<name>bottom</name>
		<pose>Unspecified</pose>
		<truncated>0</truncated>
		<difficult>0</difficult>
		<bndbox>
			<xmin>227</xmin>
			<ymin>312</ymin>
			<xmax>258</xmax>
			<ymax>355</ymax>
		</bndbox>
	</object>
	<object>
		<name>bottom</name>
		<pose>Unspecified</pose>
		<truncated>0</truncated>
		<difficult>0</difficult>
		<bndbox>
			<xmin>270</xmin>
			<ymin>323</ymin>
			<xmax>306</xmax>
			<ymax>373</ymax>
		</bndbox>
	</object>
	<object>
		<name>bottom</name>
		<pose>Unspecified</pose>
		<truncated>0</truncated>
		<difficult>0</difficult>
		<bndbox>
			<xmin>309</xmin>
			<ymin>341</ymin>
			<xmax>345</xmax>
			<ymax>389</ymax>
		</bndbox>
	</object>
	<object>
		<name>bottom</name>
		<pose>Unspecified</pose>
		<truncated>0</truncated>
		<difficult>0</difficult>
		<bndbox>
			<xmin>347</xmin>
			<ymin>359</ymin>
			<xmax>387</xmax>
			<ymax>411</ymax>
		</bndbox>
	</object>
</annotation>
