<?xml version="1.0" encoding="utf-8"?><annotation>
	<folder>images</folder>
	<filename>18_19_16_22_17_24_L_H_L_L_L_L_0635.png</filename>
	<path>C:\Users\Jesper\Desktop\DL\images\18_19_16_22_17_24_L_H_L_L_L_L_0635.png</path>
	<source>
		<database>Unknown</database>
	</source>
	<size>
		<width>350</width>
		<height>350</height>
		<depth>3</depth>
	</size>
	<segmented>0</segmented>
	<object>
		<name>top</name>
		<pose>Unspecified</pose>
		<truncated>0</truncated>
		<difficult>0</difficult>
		<bndbox>
			<xmin>3</xmin>
			<ymin>22</ymin>
			<xmax>41</xmax>
			<ymax>64</ymax>
		</bndbox>
	</object>
	<object>
		<name>top</name>
		<pose>Unspecified</pose>
		<truncated>0</truncated>
		<difficult>0</difficult>
		<bndbox>
			<xmin>61</xmin>
			<ymin>20</ymin>
			<xmax>101</xmax>
			<ymax>65</ymax>
		</bndbox>
	</object>
	<object>
		<name>top</name>
		<pose>Unspecified</pose>
		<truncated>0</truncated>
		<difficult>0</difficult>
		<bndbox>
			<xmin>121</xmin>
			<ymin>17</ymin>
			<xmax>155</xmax>
			<ymax>55</ymax>
		</bndbox>
	</object>
	<object>
		<name>top</name>
		<pose>Unspecified</pose>
		<truncated>0</truncated>
		<difficult>0</difficult>
		<bndbox>
			<xmin>176</xmin>
			<ymin>10</ymin>
			<xmax>224</xmax>
			<ymax>60</ymax>
		</bndbox>
	</object>
	<object>
		<name>top</name>
		<pose>Unspecified</pose>
		<truncated>0</truncated>
		<difficult>0</difficult>
		<bndbox>
			<xmin>241</xmin>
			<ymin>10</ymin>
			<xmax>281</xmax>
			<ymax>56</ymax>
		</bndbox>
	</object>
	<object>
		<name>top</name>
		<pose>Unspecified</pose>
		<truncated>0</truncated>
		<difficult>0</difficult>
		<bndbox>
			<xmin>298</xmin>
			<ymin>6</ymin>
			<xmax>347</xmax>
			<ymax>64</ymax>
		</bndbox>
	</object>
	<object>
		<name>bottom</name>
		<pose>Unspecified</pose>
		<truncated>0</truncated>
		<difficult>0</difficult>
		<bndbox>
			<xmin>23</xmin>
			<ymin>240</ymin>
			<xmax>66</xmax>
			<ymax>283</ymax>
		</bndbox>
	</object>
	<object>
		<name>bottom</name>
		<pose>Unspecified</pose>
		<truncated>0</truncated>
		<difficult>0</difficult>
		<bndbox>
			<xmin>67</xmin>
			<ymin>260</ymin>
			<xmax>114</xmax>
			<ymax>310</ymax>
		</bndbox>
	</object>
	<object>
		<name>bottom</name>
		<pose>Unspecified</pose>
		<truncated>0</truncated>
		<difficult>0</difficult>
		<bndbox>
			<xmin>127</xmin>
			<ymin>230</ymin>
			<xmax>166</xmax>
			<ymax>270</ymax>
		</bndbox>
	</object>
	<object>
		<name>bottom</name>
		<pose>Unspecified</pose>
		<truncated>0</truncated>
		<difficult>0</difficult>
		<bndbox>
			<xmin>180</xmin>
			<ymin>285</ymin>
			<xmax>230</xmax>
			<ymax>334</ymax>
		</bndbox>
	</object>
	<object>
		<name>bottom</name>
		<pose>Unspecified</pose>
		<truncated>0</truncated>
		<difficult>0</difficult>
		<bndbox>
			<xmin>239</xmin>
			<ymin>223</ymin>
			<xmax>280</xmax>
			<ymax>267</ymax>
		</bndbox>
	</object>
	<object>
		<name>bottom</name>
		<pose>Unspecified</pose>
		<truncated>0</truncated>
		<difficult>0</difficult>
		<bndbox>
			<xmin>282</xmin>
			<ymin>292</ymin>
			<xmax>340</xmax>
			<ymax>344</ymax>
		</bndbox>
	</object>
</annotation>